CHANGELOG
LICENSE
MANIFEST.in
README.md
WAIVER
WAIVER.asc
erc20_requirements.txt
requirements.txt
setup.cfg
setup.py
test_requirements.txt
chaind/eth/__init__.py
chaind/eth/cache.py
chaind/eth/chain.py
chaind/eth/dispatch.py
chaind/eth/settings.py
chaind/eth/cli/csv.py
chaind/eth/cli/output.py
chaind/eth/data/config/config.ini
chaind/eth/data/config/syncer/config.ini
chaind/eth/runnable/queuer.py
chaind/eth/runnable/send.py
chaind/eth/runnable/syncer.py
chaind/eth/token/__init__.py
chaind/eth/token/base.py
chaind/eth/token/erc20.py
chaind/eth/token/gas.py
chaind/eth/token/process.py
chaind_eth.egg-info/PKG-INFO
chaind_eth.egg-info/SOURCES.txt
chaind_eth.egg-info/dependency_links.txt
chaind_eth.egg-info/entry_points.txt
chaind_eth.egg-info/requires.txt
chaind_eth.egg-info/top_level.txt
tests/test_tx.py