Metadata-Version: 2.1
Name: chaind-eth
Version: 0.4.0
Summary: Queue server for ethereum
Home-page: https://git.defalsify.org/chaind-eth
Author: Louis Holbrook
Author-email: dev@holbrook.no
License: AGPLv3+
Keywords: dlt,blockchain,cryptocurrency,ethereum
Classifier: Programming Language :: Python :: 3
Classifier: Operating System :: OS Independent
Classifier: Development Status :: 3 - Alpha
Classifier: Environment :: Console
Classifier: Intended Audience :: Developers
Classifier: License :: OSI Approved :: GNU Affero General Public License v3 or later (AGPLv3+)
Classifier: Topic :: Internet
Requires-Python: >=3.8
Provides-Extra: erc20
License-File: LICENSE
